{
    "resumeInfo": {
        "title": "Resume",
        "linkClass": "info-link",
        "link": "https://drive.google.com/uc?export=download&id=1kAcLoWS1vTyBMn3FgfmW9qRpruKEs4Yx",
        "iconClass": "fa-solid fa-file-arrow-down"
    },
    "langSkillInfo": [
        {
            "topic": "Thai",
            "detail": "Native speak, read and write"
        },
        {
            "topic": "English",
            "detail": "Intermediate speak, read and write"
        },
        {
            "topic": "Japanese",
            "detail": "Japanese-Language Proficiency Test Level N3"
        }
    ],
    "personalInfo": [
        {
            "topic": "Name",
            "detail": "Ratchagree Amornlikitsin"
        },
        {
            "topic": "Date of birth",
            "detail": "12 March 1997"
        },
        {
            "topic": "Email",
            "detail": "ratchagree@gmail.com"
        }
    ],
    "proSkillInfo": [
        {
            "topic": "",
            "detail": "HTML5, CSS3, JavaScript"
        },
        {
            "topic": "",
            "detail": "ReactJS"
        },
        {
            "topic": "",
            "detail": "Python"
        },
        {
            "topic": "",
            "detail": "Java"
        },
        {
            "topic": "",
            "detail": "C"
        },
        {
            "topic": "",
            "detail": "VBA Excel"
        },
        {
            "topic": "",
            "detail": "MATLAB (m-script)"
        },
        {
            "topic": "",
            "detail": "Simulink, Stateflow"
        }
    ],
    "eduInfo": [
        {
            "topic": "Thammasat University",
            "detail": "Bachelor’s Degree in Electrical Engineering (2015 – 2019)",
            "list": []
        },
        {
            "topic": "Rittiyawannalai School, Bangkok",
            "detail": "Certificate of General Education (2009 – 2015)",
            "list": []
        }
    ],
    "workInfo": [
        {
            "topic": "Software Engineer",
            "detail": "Toyota Tsusho Denso Electronics Thailand Co., Ltd (2019 - Present)",
            "list": [
                "Development and Testing on ECU software (Embedded) by using MATLAB, Simulink and C language",
                "Create test pattern for software testing to confirm functional of software work product",
                "Develop tool for support automate task by using M-script and VBA Excel",
                "Organize collaboration activity with the university to promote the company"
            ]
        },
        {
            "topic": "Trainee",
            "detail": "Shinetsu Works Co., Ltd. (2018 : Jun – Aug)",
            "list": [
                "Participate industrial Internship Program in Japan",
                "Operate product assembly line",
                "Products testing"
            ]
        }
    ],
    "awardInfo": [
        {
            "topic": "",
            "detail": "2018 : ENGR Academic Excellence Award",
            "list": []
        },
        {
            "topic": "",
            "detail": "2019 : Certificates of Participation in The TESA TopGun Rally 2019 by Thai Embedded Systems Association (TESA)",
            "list": []
        }
    ],
    "projectInfo": [
        {
            "title": "25 + 5 Clock",
            "link": "https://codepen.io/ratchagreea/pen/PoRNgrq",
            "img": "https://codepen.io/ratchagreea/pen/PoRNgrq/image/small.png"
        },
        {
            "title": "Calculator",
            "link": "https://codepen.io/ratchagreea/pen/jOzPNBR",
            "img": "https://codepen.io/ratchagreea/pen/jOzPNBR/image/small.png"
        },
        {
            "title": "Drum Machine",
            "link": "https://codepen.io/ratchagreea/pen/rNdBxEW",
            "img": "https://codepen.io/ratchagreea/pen/rNdBxEW/image/small.png"
        },
        {
            "title": "Random Quote Machine",
            "link": "https://codepen.io/ratchagreea/pen/XWZxmoL",
            "img": "https://codepen.io/ratchagreea/pen/XWZxmoL/image/small.png"
        },
        {
            "title": "Markdown Previewer",
            "link": "https://codepen.io/ratchagreea/pen/ExQMmXa",
            "img": "https://codepen.io/ratchagreea/pen/ExQMmXa/image/small.png"
        },
        {
            "title": "Income - Expense",
            "link": "https://codepen.io/ratchagreea/pen/GRxroXx",
            "img": "https://codepen.io/ratchagreea/pen/GRxroXx/image/small.png"
        },
        {
            "title": "Product Landing Page",
            "link": "https://codepen.io/ratchagreea/pen/zYpQZmB",
            "img": "https://codepen.io/ratchagreea/pen/zYpQZmB/image/small.png"
        },
        {
            "title": "Survey Form",
            "link": "https://codepen.io/ratchagreea/pen/WNdmKYa",
            "img": "https://codepen.io/ratchagreea/pen/WNdmKYa/image/small.png"
        },
        {
            "title": "Technical Documentation Page",
            "link": "https://codepen.io/ratchagreea/pen/qBxWypY",
            "img": "https://codepen.io/ratchagreea/pen/qBxWypY/image/small.png"
        }
    ],
    "showAll": {
        "title": "Show all",
        "link": "https://codepen.io/ratchagreea",
        "linkClass": "btn-show-all",
        "iconClass": "fa-solid fa-folder-open"
    },
    "contactInfo": [
        {
            "title": "linkedin",
            "linkClass": "contact-link",
            "link": "https://www.linkedin.com/in/ratchagree-amornlikitsin-55374222a/",
            "iconClass": "fa-brands fa-linkedin"
        },
        {
            "title": "GitHub",
            "linkClass": "contact-link",
            "link": "https://github.com/RatchagreeA",
            "iconClass": "fab fa-github"
        },
        {
            "title": "CodePen",
            "linkClass": "contact-link",
            "link": "https://codepen.io/ratchagreea",
            "iconClass": "fa-brands fa-codepen"
        },
        {
            "title": "Send a mail",
            "linkClass": "contact-link",
            "link": "mailto:ratchagree@gmail.com",
            "iconClass": "fas fa-at"
        },
        {
            "title": "Call me",
            "linkClass": "contact-link",
            "link": "tel:+66892358488",
            "iconClass": "fas fa-mobile-alt"
        }
    ]
}
